tvc_benchmarker/__init__.py
tvc_benchmarker/__main__.py
tvc_benchmarker/add_method.py
tvc_benchmarker/dfc_calc.py
tvc_benchmarker/dfc_evaluate.py
tvc_benchmarker/get_data.py
tvc_benchmarker/misc.py
tvc_benchmarker/plot.py
tvc_benchmarker/run.py
tvc_benchmarker/send_method.py
tvc_benchmarker/data/data/sim-1_data.csv
tvc_benchmarker/data/data/sim-2_data.csv
tvc_benchmarker/data/data/sim-3_data.csv
tvc_benchmarker/data/data/sim-4_data.csv
tvc_benchmarker/data/dfc/sim-1_dfc.csv
tvc_benchmarker/data/dfc/sim-2_dfc.csv
tvc_benchmarker/data/dfc/sim-3_dfc.csv
tvc_benchmarker/data/dfc/sim-4_dfc.csv
tvc_benchmarker/data/hrf/hrf_TR2.npy
tvc_benchmarker/data/routine_params/0.1.json
tvc_benchmarker/data/routine_params/1.0.json
tvc_benchmarker/data/routine_params/1.0sup.json
tvc_benchmarker-1.0.1.dist-info/DESCRIPTION.rst
tvc_benchmarker-1.0.1.dist-info/METADATA
tvc_benchmarker-1.0.1.dist-info/RECORD
tvc_benchmarker-1.0.1.dist-info/WHEEL
tvc_benchmarker-1.0.1.dist-info/metadata.json
tvc_benchmarker-1.0.1.dist-info/top_level.txt
