Metadata-Version: 2.0
Name: tvc-benchmarker
Version: 1.0.1
Summary: tvc_benchmarker is a package that compares different time-varying functoinal connectivity methods against eachother (neuroimaging/fmri).
Home-page: https://www.github.com/wiheto/tvc_benchmarker
Author: William Hedley Thompson
Author-email: UNKNOWN
License: UNKNOWN
Platform: UNKNOWN
Requires-Dist: matplotlib (>=1.5.3)
Requires-Dist: numpy (>=1.14.0)
Requires-Dist: pandas (>=0.22.0)
Requires-Dist: pymc3 (>=3.2)
Requires-Dist: requests (>=2.14.2)
Requires-Dist: scipy (>=0.18.1)
Requires-Dist: seaborn (>=0.7.0)
Requires-Dist: setuptools (>=35.0.2)
Requires-Dist: tabulate (>=0.7.7)
Requires-Dist: teneto (>=0.2.7b)
